[{
  "id": 1,
  "status": "standby",
  "company": "Browsezoom",
  "work_description": "Donec ut mauris eget massa tempor convallis. Nulla neque libero, convallis eget, eleifend luctus, ultricies eu, nibh.",
  "working_area__general": "EKI",
  "working_area__exact": "5.4",
  "working_days__nh": false,
  "working_days__ph": false,
  "working_days__bh": true,
  "valid_from": "5/17/2020",
  "valid_until": "7/4/2020",
  "person_in_charge": "Glory Delatour"
}, {
  "id": 2,
  "status": "closed",
  "company": "Twitterbridge",
  "work_description": "Morbi non lectus. Aliquam sit amet diam in magna bibendum imperdiet.",
  "working_area__general": "EKI",
  "working_area__exact": "cafeteria",
  "working_days__nh": true,
  "working_days__ph": true,
  "working_days__bh": true,
  "valid_from": "4/3/2020",
  "valid_until": "7/22/2020",
  "person_in_charge": "Jim Crimp"
}, {
  "id": 3,
  "status": "standby",
  "company": "Topiclounge",
  "work_description": "Proin interdum mauris non ligula pellentesque ultrices. Phasellus id sapien in sapien iaculis congue.",
  "working_area__general": "WKI",
  "working_area__exact": "loading bay",
  "working_days__nh": true,
  "working_days__ph": true,
  "working_days__bh": false,
  "valid_from": "6/11/2020",
  "valid_until": "8/19/2020",
  "person_in_charge": "Dene Yellop"
}, {
  "id": 4,
  "status": "open",
  "company": "Skinte",
  "work_description": "Nam dui. Proin leo odio, porttitor id, consequat in, consequat ut, nulla.",
  "working_area__general": "EKI",
  "working_area__exact": "loading bay",
  "working_days__nh": true,
  "working_days__ph": false,
  "working_days__bh": true,
  "valid_from": "5/4/2020",
  "valid_until": "3/23/2021",
  "person_in_charge": "Zara Costello"
}, {
  "id": 5,
  "status": "closed",
  "company": "Bubblemix",
  "work_description": "Integer tincidunt ante vel ipsum. Praesent blandit lacinia erat.",
  "working_area__general": "EKI",
  "working_area__exact": "tunnel",
  "working_days__nh": false,
  "working_days__ph": false,
  "working_days__bh": false,
  "valid_from": "1/25/2021",
  "valid_until": "12/2/2020",
  "person_in_charge": "Keir Penniall"
}, {
  "id": 6,
  "status": "closed",
  "company": "Twiyo",
  "work_description": "Nam ultrices, libero non mattis pulvinar, nulla pede ullamcorper augue, a suscipit nulla elit ac nulla.",
  "working_area__general": "WKI",
  "working_area__exact": "Ensemble",
  "working_days__nh": true,
  "working_days__ph": false,
  "working_days__bh": false,
  "valid_from": "8/26/2020",
  "valid_until": "3/4/2021",
  "person_in_charge": "Florencia Kopfen"
}, {
  "id": 7,
  "status": "closed",
  "company": "Youopia",
  "work_description": "Nulla justo. Aliquam quis turpis eget elit sodales scelerisque. Mauris sit amet eros.",
  "working_area__general": "WKI",
  "working_area__exact": "6.3",
  "working_days__nh": false,
  "working_days__ph": true,
  "working_days__bh": true,
  "valid_from": "3/9/2021",
  "valid_until": "12/2/2020",
  "person_in_charge": "Fairleigh Alliband"
}, {
  "id": 8,
  "status": "open",
  "company": "Kaymbo",
  "work_description": "Etiam vel augue.",
  "working_area__general": "EKI",
  "working_area__exact": "6.3",
  "working_days__nh": true,
  "working_days__ph": false,
  "working_days__bh": false,
  "valid_from": "2/4/2021",
  "valid_until": "3/17/2021",
  "person_in_charge": "Nanny Burgan"
}, {
  "id": 9,
  "status": "closed",
  "company": "Plambee",
  "work_description": "Nullam sit amet turpis elementum ligula vehicula consequat. Morbi a ipsum.",
  "working_area__general": "EKI",
  "working_area__exact": "4.2",
  "working_days__nh": true,
  "working_days__ph": true,
  "working_days__bh": true,
  "valid_from": "1/18/2021",
  "valid_until": "2/9/2021",
  "person_in_charge": "Melina Ventura"
}, {
  "id": 10,
  "status": "standby",
  "company": "Youfeed",
  "work_description": "Maecenas rhoncus aliquam lacus. Morbi quis tortor id nulla ultrices aliquet. Maecenas leo odio, condimentum id, luctus nec, molestie sed, justo.",
  "working_area__general": "EKI",
  "working_area__exact": "4.2",
  "working_days__nh": true,
  "working_days__ph": true,
  "working_days__bh": true,
  "valid_from": "6/15/2020",
  "valid_until": "6/27/2020",
  "person_in_charge": "Chauncey Chattell"
}]
